build_shred/memory_mapped.v
/* Generated by Yosys 0.33 (git sha1 2584903a060) */

module \$__GEMCARRY4_ (S, DI, CIN, CYINIT, CO, O);
  wire _00_;
  wire _01_;
  wire _02_;
  wire _03_;
  wire _04_;
  wire _05_;
  wire _06_;
  wire _07_;
  wire _08_;
  wire _09_;
  wire _10_;
  wire _11_;
  input CIN;
  wire CIN;
  output [3:0] CO;
  wire [3:0] CO;
  input CYINIT;
  wire CYINIT;
  wire [4:0] Cv;
  input [3:0] DI;
  wire [3:0] DI;
  output [3:0] O;
  wire [3:0] O;
  input [3:0] S;
  wire [3:0] S;
  assign _00_ = _11_ & DI[0];
  assign _01_ = S[1] & Cv[1];
  assign _02_ = _08_ & DI[1];
  assign _03_ = S[2] & Cv[2];
  assign _04_ = _09_ & DI[2];
  assign _05_ = S[3] & Cv[3];
  assign _06_ = _10_ & DI[3];
  assign _07_ = S[0] & Cv[0];
  assign _08_ = ~ S[1];
  assign _09_ = ~ S[2];
  assign _10_ = ~ S[3];
  assign _11_ = ~ S[0];
  assign Cv[0] = CYINIT | CIN;
  assign Cv[1] = _07_ | _00_;
  assign Cv[2] = _01_ | _02_;
  assign Cv[3] = _03_ | _04_;
  assign CO[3] = _05_ | _06_;
  assign O[0] = S[0] ^ Cv[0];
  assign O[1] = S[1] ^ Cv[1];
  assign O[2] = S[2] ^ Cv[2];
  assign O[3] = S[3] ^ Cv[3];
  assign CO[2:0] = Cv[3:1];
  assign Cv[4] = CO[3];
endmodule

module \$__GEMDSP_ (CLK, A, B, C, D, USE_PREADD, MODE, P);
  wire [47:0] _00_;
  wire [26:0] _01_;
  wire [47:0] _02_;
  wire _03_;
  wire _04_;
  input [26:0] A;
  wire [26:0] A;
  wire [26:0] AD;
  input [17:0] B;
  wire [17:0] B;
  input [47:0] C;
  wire [47:0] C;
  input CLK;
  wire CLK;
  input [26:0] D;
  wire [26:0] D;
  wire [44:0] M;
  input [1:0] MODE;
  wire [1:0] MODE;
  output [47:0] P;
  reg [47:0] P = 48'h000000000000;
  input USE_PREADD;
  wire USE_PREADD;
  assign _01_ = $signed(A) + $signed(D);
  assign _02_ = $signed(P) + $signed({ M[44], M[44], M[44], M });
  assign M = $signed(AD) * $signed(B);
  always @(posedge CLK)
    P <= _00_;
  function [47:0] _09_;
    input [47:0] a;
    input [95:0] b;
    input [1:0] s;
    casez (s) // synopsys parallel_case
      2'b?1:
        _09_ = b[47:0];
      2'b1?:
        _09_ = b[95:48];
      default:
        _09_ = a;
    endcase
  endfunction
  assign _00_ = _09_(_02_, { C, M[44], M[44], M[44], M }, { _04_, _03_ });
  assign _03_ = MODE == 2'h1;
  assign _04_ = ! MODE;
  assign AD = USE_PREADD ? _01_ : A;
endmodule

module \$__GEMSRL32_ (CLK, D, CE, A, Q, Q31);
  input [4:0] A;
  wire [4:0] A;
  input CE;
  wire CE;
  input CLK;
  wire CLK;
  input D;
  wire D;
  output Q;
  wire Q;
  output Q31;
  wire Q31;
  reg [31:0] sr = 32'd0;
  always @(posedge CLK)
    if (CE) sr <= { sr[30:0], D };
  wire [31:0] _2_ = sr;
  assign Q = _2_[A +: 1];
  assign Q31 = sr[31];
endmodule

module CARRY4(S, DI, CIN, CYINIT, CO, O);
  input CIN;
  wire CIN;
  output [3:0] CO;
  wire [3:0] CO;
  input CYINIT;
  wire CYINIT;
  input [3:0] DI;
  wire [3:0] DI;
  output [3:0] O;
  wire [3:0] O;
  input [3:0] S;
  wire [3:0] S;
  \$__GEMCARRY4_  _TECHMAP_REPLACE_ (
    .CIN(CIN),
    .CO(CO),
    .CYINIT(CYINIT),
    .DI(DI),
    .O(O),
    .S(S)
  );
endmodule

module DSP48E2(CLK, A, B, C, D, USE_PREADD, MODE, P);
  input [26:0] A;
  wire [26:0] A;
  input [17:0] B;
  wire [17:0] B;
  input [47:0] C;
  wire [47:0] C;
  input CLK;
  wire CLK;
  input [26:0] D;
  wire [26:0] D;
  input [1:0] MODE;
  wire [1:0] MODE;
  output [47:0] P;
  wire [47:0] P;
  input USE_PREADD;
  wire USE_PREADD;
  \$__GEMDSP_  _TECHMAP_REPLACE_ (
    .A(A),
    .B(B),
    .C(C),
    .CLK(CLK),
    .D(D),
    .MODE(MODE),
    .P(P),
    .USE_PREADD(USE_PREADD)
  );
endmodule

module SRLC32E(CLK, D, CE, A, Q, Q31);
  input [4:0] A;
  wire [4:0] A;
  input CE;
  wire CE;
  input CLK;
  wire CLK;
  input D;
  wire D;
  output Q;
  wire Q;
  output Q31;
  wire Q31;
  \$__GEMSRL32_  _TECHMAP_REPLACE_ (
    .A(A),
    .CE(CE),
    .CLK(CLK),
    .D(D),
    .Q(Q),
    .Q31(Q31)
  );
endmodule

module macro_smoke(clk, a0, a1, d0, b0, b1, c0, mode, x, y, tap, ser_in, ser_en, acc0, acc1, sum, delayed, delayed31, scratch);
  wire [7:0] _0_;
  input [26:0] a0;
  wire [26:0] a0;
  input [26:0] a1;
  wire [26:0] a1;
  output [47:0] acc0;
  wire [47:0] acc0;
  output [47:0] acc1;
  wire [47:0] acc1;
  input [17:0] b0;
  wire [17:0] b0;
  input [17:0] b1;
  wire [17:0] b1;
  input [47:0] c0;
  wire [47:0] c0;
  wire [4:0] carry;
  input clk;
  wire clk;
  reg [7:0] cnt;
  input [26:0] d0;
  wire [26:0] d0;
  output delayed;
  wire delayed;
  output delayed31;
  wire delayed31;
  wire [3:0] \g_carry[0].co_i ;
  wire [3:0] \g_carry[1].co_i ;
  wire [3:0] \g_carry[2].co_i ;
  wire [3:0] \g_carry[3].co_i ;
  input [1:0] mode;
  wire [1:0] mode;
  wire [15:0] p;
  output [7:0] scratch;
  wire [7:0] scratch;
  input ser_en;
  wire ser_en;
  input ser_in;
  wire ser_in;
  output [16:0] sum;
  wire [16:0] sum;
  input [4:0] tap;
  wire [4:0] tap;
  input [15:0] x;
  wire [15:0] x;
  input [15:0] y;
  wire [15:0] y;
  assign _0_ = cnt + 8'h01;
  always @(posedge clk)
    cnt <= _0_;
  assign p = x ^ y;
  assign scratch = cnt ^ { x[3:0], y[3:0] };
  CARRY4 \g_carry[0].u_c4  (
    .CIN(1'h0),
    .CO(\g_carry[0].co_i ),
    .CYINIT(1'h0),
    .DI(x[3:0]),
    .O(sum[3:0]),
    .S(p[3:0])
  );
  CARRY4 \g_carry[1].u_c4  (
    .CIN(\g_carry[0].co_i [3]),
    .CO(\g_carry[1].co_i ),
    .CYINIT(1'h0),
    .DI(x[7:4]),
    .O(sum[7:4]),
    .S(p[7:4])
  );
  CARRY4 \g_carry[2].u_c4  (
    .CIN(\g_carry[1].co_i [3]),
    .CO(\g_carry[2].co_i ),
    .CYINIT(1'h0),
    .DI(x[11:8]),
    .O(sum[11:8]),
    .S(p[11:8])
  );
  CARRY4 \g_carry[3].u_c4  (
    .CIN(\g_carry[2].co_i [3]),
    .CO(\g_carry[3].co_i ),
    .CYINIT(1'h0),
    .DI(x[15:12]),
    .O(sum[15:12]),
    .S(p[15:12])
  );
  DSP48E2 u_dsp0 (
    .A(a0),
    .B(b0),
    .C(c0),
    .CLK(clk),
    .D(d0),
    .MODE(mode),
    .P(acc0),
    .USE_PREADD(1'h1)
  );
  DSP48E2 u_dsp1 (
    .A(a1),
    .B(b1),
    .C(48'h000000000000),
    .CLK(clk),
    .D(27'h0000000),
    .MODE(2'h1),
    .P(acc1),
    .USE_PREADD(1'h0)
  );
  SRLC32E u_srl (
    .A(tap),
    .CE(ser_en),
    .CLK(clk),
    .D(ser_in),
    .Q(delayed),
    .Q31(delayed31)
  );
  assign carry = { \g_carry[3].co_i [3], \g_carry[2].co_i [3], \g_carry[1].co_i [3], \g_carry[0].co_i [3], 1'h0 };
  assign sum[16] = \g_carry[3].co_i [3];
endmodule

bench/macro_bench.sv
// Scaled macro benchmark.
//
// macro_smoke.sv proves correctness on 7 macros. It cannot show throughput,
// because at 102 cells it maps to a SINGLE boomerang partition either way --
// and GEM's script size scales with PARTITIONS, not with gate count. A 104x
// reduction in AIG cells therefore shrank the script by only 26%, leaving the
// run dominated by grid-barrier latency rather than by memory bandwidth.
//
// This design exists to move the workload into the regime the optimisation
// actually targets. Three properties matter, and each is deliberate:
//
//   1. MANY ENDPOINTS. Partitions come from endpoints, not gates. Every lane
//      carries a 48-bit registered accumulator, so LANES=64 gives 3072 flop
//      endpoints and forces the design across many partitions. That is what
//      makes the shredded script large enough to saturate DRAM.
//
//   2. MACRO -> BOOLEAN. flags[l] compares a CARRY4 sum against a constant.
//      That is exactly the dependency that was silently broken (a macro
//      result reaching AND-gate logic), so the benchmark regression-tests the
//      fix rather than merely exercising macros in isolation.
//
//   3. MACRO -> MACRO. Each lane's carry chain feeds CO[3] into the next
//      block's CIN, the dependency the problem statement names explicitly.
//
// Lanes are perturbed by their index so Yosys cannot common-subexpression
// them into one lane. Outputs are XOR-reductions so every lane stays
// observable -- an unobservable lane would be optimised away and the gate
// count would silently collapse.
//
// Style note: this deliberately avoids SystemVerilog casts, unpacked arrays
// in port connections and empty port connections. All three are legal, and
// all three are places where synthesiser frontends differ. Everything here is
// Verilog-2001-shaped so the two synthesis flows cannot disagree about it.
//
// Sweep with bench/gen_bench.sh; LANES is the only knob.

module macro_bench #(
    parameter LANES = 16
) (
    input  wire               clk,
    input  wire signed [26:0] a_in, d_in,
    input  wire signed [17:0] b_in,
    input  wire signed [47:0] c_in,
    input  wire        [1:0]  mode,
    input  wire        [15:0] x_in, y_in,
    input  wire        [4:0]  tap,
    input  wire               ser_in, ser_en,
    output reg  signed [47:0] acc_xor,
    output reg         [16:0] sum_xor,
    output wire [LANES-1:0]   flags,
    output reg                delayed_xor
);

  // Flattened per-lane results. Packed, not unpacked: an unpacked array
  // element in an instance port connection is the kind of thing frontends
  // disagree about.
  wire [48*LANES-1:0] acc_flat;
  wire [17*LANES-1:0] sum_flat;
  wire    [LANES-1:0] delayed;

  genvar l, i;
  generate
    for (l = 0; l < LANES; l = l + 1) begin : g_lane

      // --- per-lane perturbation ------------------------------------------
      // Without this every lane is structurally identical and Yosys folds
      // them into one, which would defeat the whole point of scaling.
      localparam [26:0] PA = l;
      localparam [26:0] PD = l * 3;
      localparam [17:0] PB = l * 5;
      localparam [47:0] PC = l * 7;
      localparam [15:0] PX = l * 11;
      localparam [15:0] PY = l * 13;
      localparam [4:0]  PT = l;

      wire signed [26:0] a_l = a_in ^ PA;
      wire signed [26:0] d_l = d_in ^ PD;
      wire signed [17:0] b_l = b_in ^ PB;
      wire signed [47:0] c_l = c_in ^ PC;
      wire        [15:0] x_l = x_in ^ PX;
      wire        [15:0] y_l = y_in ^ PY;

      // --- MAC ------------------------------------------------------------
      wire signed [47:0] p_l;
      DSP48E2 u_dsp (.CLK(clk), .A(a_l), .B(b_l), .C(c_l), .D(d_l),
                     .USE_PREADD(1'b1), .MODE(mode), .P(p_l));

      // A 48-bit accumulator per lane. This is the endpoint multiplier: it is
      // what turns a small design into a many-partition one.
      reg signed [47:0] acc_r;
      always @(posedge clk) acc_r <= acc_r ^ p_l;
      assign acc_flat[48*l +: 48] = acc_r;

      // --- 16-bit adder as a real CARRY4 chain ----------------------------
      wire [16:0] sum_l;
      wire [15:0] prop = x_l ^ y_l;
      wire [4:0]  carry;
      assign carry[0] = 1'b0;
      for (i = 0; i < 4; i = i + 1) begin : g_carry
        wire [3:0] co_i;
        CARRY4 u_c4 (.S(prop[i*4 +: 4]), .DI(x_l[i*4 +: 4]),
                     .CIN(carry[i]), .CYINIT(1'b0),
                     .CO(co_i), .O(sum_l[i*4 +: 4]));
        assign carry[i+1] = co_i[3];
      end
      assign sum_l[16] = carry[4];
      assign sum_flat[17*l +: 17] = sum_l;

      // --- MACRO -> BOOLEAN: the dependency that was broken ---------------
      // A comparator on the CARRY4 result. Ordinary AND-gate logic consuming
      // a word-level macro output.
      assign flags[l] = (sum_l > 17'd100);

      // --- delay line -----------------------------------------------------
      wire q31_unused;
      SRLC32E u_srl (.CLK(clk), .D(ser_in ^ PA[0]), .CE(ser_en),
                     .A(tap ^ PT), .Q(delayed[l]), .Q31(q31_unused));
    end
  endgenerate

  // XOR-reduce so every lane remains observable at a top-level port without
  // needing LANES x 48 primary outputs.
  integer k;
  always @* begin
    acc_xor     = 48'd0;
    sum_xor     = 17'd0;
    delayed_xor = 1'b0;
    for (k = 0; k < LANES; k = k + 1) begin
      acc_xor     = acc_xor ^ acc_flat[48*k +: 48];
      sum_xor     = sum_xor ^ sum_flat[17*k +: 17];
      delayed_xor = delayed_xor ^ delayed[k];
    end
  end

endmodule

build_bench16_native/in.vcd
$timescale 1ps $end
$scope module macro_bench $end
$var wire 27 ! a_in $end
$var wire 18 " b_in $end
$var wire 48 # c_in $end
$var wire 1 $ clk $end
$var wire 27 % d_in $end
$var wire 2 & mode $end
$var wire 1 ' ser_en $end
$var wire 1 ( ser_in $end
$var wire 5 ) tap $end
$var wire 16 * x_in $end
$var wire 16 + y_in $end
$upscope $end
$enddefinitions $end
#0
b001000100110010110110001111 !
b100100011011011101 "
b110011010110000111011000111100010110101011011111 #
0$
b110000111000011010111011110 %
b00 &
0'
0(
b01111 )
b1100001011001110 *
b0111001100010001 +
#500
1$
#1000
0$
b011110001110010100010000011 !
b101001101100111011 "
b110010011110100101100001001011100111011010010110 #
b001101011011111110011001001 %
b00 &
0'
0(
b11100 )
b1101010111110100 *
b0110001111001010 +
#1500
1$
#2000
0$
b011011101100100111010010100 !
b100110111000000100 "
b110001000110010011000011001001001100100110000101 #
b000000001000101000000101101 %
b10 &
0'
0(
b10111 )
b1100110101000100 *
b0011101010010000 +
#2500
1$
#3000
0$
b100101110101010111010100110 !
b111100011111110101 "
b111001101100001100011010001010111000111100011111 #
b010100010100001100010001100 %
b00 &
0'
0(
b10100 )
b1000101010011010 *
b0000001001011011 +
#3500
1$
#4000
0$
b111100000110110000010100010 !
b111000011001100010 "
b101011111011110101100001100101101001100111001111 #
b001101110111001100001110110 %
b11 &
0'
1(
b00000 )
b1000011100010010 *
b0011100011000000 +
#4500
1$
#5000
0$
b110000111000000111101000100 !
b011100000001100101 "
b011111101110110111110000011011010011111111101111 #
b100011011000100000110100100 %
b00 &
0'
0(
b10101 )
b0011100000000010 *
b1100001011001101 +
#5500
1$
#6000
0$
b011101011010100010010010100 !
b111100111100011001 "
b111011010010111101001010001011110010000010101010 #
b000001011000000001011001011 %
b01 &
1'
1(
b10001 )
b1110110000010100 *
b1010010001101101 +
#6500
1$
#7000
0$
b000110011001100110011110001 !
b001011111001011110 "
b111111100001011110100001000111010100010110011010 #
b101110010100000001100111111 %
b11 &
0'
0(
b10111 )
b0101010100101011 *
b1110010101000100 +
#7500
1$
#8000
0$
b101110001011001100110011101 !
b111110010010011100 "
b100000000011010010110110000100001010100111110111 #
b111011111011101010010001111 %
b11 &
0'
1(
b11010 )
b1110100100000001 *
b1010101110011001 +
#8500
1$
#9000
0$
b001100001001100111111101111 !
b010011011010100110 "
b100101100110101101001000101111101010101100010011 #
b111110010011010000011100011 %
b11 &
0'
1(
b11110 )
b1000000101011010 *
b0110010010110010 +
#9500
1$
#10000
0$
b100101101100100011011010000 !
b110110100111000100 "
b011110101111000000001000110101101010111101010111 #
b001111100010010000110100111 %
b10 &
1'
0(
b01101 )
b1010101000101100 *
b0010110001001010 +
#10500
1$
#11000
0$
b010111011111101111010011110 !
b100011000111111000 "
b101100111111101011100001111110101011100111010111 #
b110001101001110101001011110 %
b10 &
1'
0(
b00010 )
b0111000001011111 *
b1010100111101100 +
#11500
1$
#12000
0$
b100000100010100000111101000 !
b000110111010000101 "
b001010011110100011000111010010000000001111100011 #
b100001010101110000111000010 %
b11 &
0'
0(
b01111 )
b1011101110010110 *
b0000011110010010 +
#12500
1$
#13000
0$
b011110000010010101011101011 !
b000010110010000111 "
b101101000001000001001110111110111100100011010110 #
b110110010010101001001010101 %
b11 &
1'
1(
b10010 )
b0110010011000010 *
b1010010110101100 +
#13500
1$
#14000
0$
b001010111001110000000001010 !
b001010110010100011 "
b001110100001100010000000100100101011010011010100 #
b111110110110100101011111111 %
b00 &
1'
0(
b10001 )
b1110101110001010 *
b1101110000111011 +
#14500
1$
#15000
0$
b100011000101111111101000111 !
b001110110110111111 "
b100000111000011001100111100010100101101010100011 #
b010110000000010011111001001 %
b11 &
1'
1(
b01011 )
b0111010110001001 *
b1110100011100101 +
#15500
1$
#16000
0$
b010001001110111101111111111 !
b101010001100001001 "
b100110111110001110001100010010010111110001101000 #
b111101010000010110010010100 %
b10 &
0'
0(
b11001 )
b1101101101100001 *
b1101001000001011 +
#16500
1$
#17000
0$
b111101000110001110110011001 !
b111000101101110010 "
b101111011001000111110000001111101101110010100111 #
b100000110011001100110010000 %
b11 &
0'
1(
b11000 )
b1000111110110101 *
b0011010010011010 +
#17500
1$
#18000
0$
b011011010001010001000111010 !
b111100110010000011 "
b011110110010100100001110010111100001100010111010 #
b110111101011100011111100010 %
b01 &
1'
1(
b00110 )
b1111000011100110 *
b1000000100110101 +
#18500
1$
#19000
0$
b011010011101010010010101110 !
b011111000010010000 "
b010110110101011011010000001101111100110111111111 #
b011010100001011110111001101 %
b01 &
0'
1(
b10001 )
b1001111110011101 *
b1100100101010100 +
#19500
1$
#20000
0$
b100111001100100110101111010 !
b010101001100010101 "
b100110011001000001110101010010010001101111000011 #
b000001110010100101011110010 %
b11 &
0'
1(
b00101 )
b1000110011111110 *
b1001010110011111 +
#20500
1$
#21000
0$
b001011100100011111011100000 !
b110111000110101100 "
b110011000110011000010111011100110011000010001100 #
b100011010001000000111110110 %
b11 &
1'
1(
b11101 )
b0100000101011010 *
b0000100001001111 +
#21500
1$
#22000
0$
b110101110111110010010110110 !
b111100011000110111 "
b000100100000100110101100010100010010101100000001 #
b000101010100111011010101000 %
b11 &
0'
0(
b00000 )
b1100000100001111 *
b1100000101101110 +
#22500
1$
#23000
0$
b010001111111110010000001011 !
b001111111110001100 "
b000111000000011101000100110001011011010001110110 #
b110011000001101100001100001 %
b10 &
0'
0(
b01001 )
b0001000111001011 *
b0010101011011111 +
#23500
1$
#24000
0$
b001010001101110100110111111 !
b010000010101010111 "
b111100111011001110000111000000100110011011000100 #
b001010110000101110001100000 %
b10 &
0'
1(
b10110 )
b0100101101100011 *
b0111010001100111 +
#24500
1$
#25000
0$
b101100111101111101000100101 !
b010100100110111010 "
b011110010100100101111111000110100011010101011110 #
b000111010011101110011001001 %
b00 &
0'
0(
b01010 )
b0110101111000001 *
b1100101111010011 +
#25500
1$
#26000
0$
b001100000010001101011000000 !
b010000100010011111 "
b010000001110001000011011110101111100111001110011 #
b111001100101101010000001010 %
b10 &
1'
1(
b00110 )
b1111011100101111 *
b1001101100001011 +
#26500
1$
#27000
0$
b011011101000000011111010010 !
b110100010010100110 "
b000001010101010011111001101111011101111010100101 #
b001110011011001000011100100 %
b00 &
0'
0(
b00001 )
b1011100000000101 *
b1111010110111011 +
#27500
1$
#28000
0$
b001010010000010010101100111 !
b011100100001011101 "
b100000011001110110110100011000010000100011001100 #
b101011011001110011101101110 %
b01 &
1'
1(
b00111 )
b1111101000011011 *
b1111100111000000 +
#28500
1$
#29000
0$
b101000010111101001000011010 !
b110011000011110101 "
b100001000011111110110001111011101101101011111111 #
b011100110110101010010100011 %
b00 &
1'
1(
b00000 )
b0110010100011000 *
b1010110011000110 +
#29500
1$
#30000
0$
b100100110110101010100100000 !
b110011011010101010 "
b101010001110101001010010001111010010101001010100 #
b101000011000010111001100100 %
b01 &
0'
1(
b01001 )
b0010000000101100 *
b1111011111001000 +
#30500
1$
#31000
0$
b001101100100111001000011001 !
b111000000010001100 "
b010011100110111100001100001001010000101000000011 #
b000100100001101100101000000 %
b11 &
0'
0(
b11101 )
b1111000001110101 *
b0100110001000001 +
#31500
1$
#32000
0$
b101111100110110001101111111 !
b001010001000000001 "
b100100001001111101101010100010100100001111101111 #
b010000001001101010001010011 %
b00 &
0'
1(
b11100 )
b1101100110111100 *
b0000100110110100 +
#32500
1$
#33000
0$
b100101110011000010000010110 !
b110100011100010100 "
b111101100101001000110111101101000000000000001011 #
b111001101001101110101110001 %
b10 &
0'
0(
b11010 )
b1101111000100110 *
b1101111010110000 +
#33500
1$
#34000
0$
b111110010100100101010101011 !
b110001111010111100 "
b100111110111101010110100001110101101110001001111 #
b100000100100010110001100110 %
b00 &
0'
0(
b01011 )
b0001100101011001 *
b0011010010101100 +
#34500
1$
#35000
0$
b100100101100100100110101011 !
b101011001001010101 "
b011011101101010111100101100001010101010100101111 #
b100101110110011010011001110 %
b00 &
0'
0(
b11110 )
b1010101001111100 *
b0110001111011011 +
#35500
1$
#36000
0$
b010010111100101101101011001 !
b100000010000110100 "
b000001000110011101111111111100101110001101000001 #
b010100110100100111011010010 %
b10 &
1'
0(
b11100 )
b0100100000000110 *
b0000010010100001 +
#36500
1$
#37000
0$
b001010000010111011100000101 !
b001100110110101100 "
b010100111110011011011011100001111000011100101101 #
b110011111010011011001111001 %
b11 &
1'
1(
b00100 )
b0101011011001110 *
b0110110111100010 +
#37500
1$
#38000
0$
b001101101000100100011110111 !
b010001000011101110 "
b000110001010111010101100101010010001011001111001 #
b110101100111001110010011110 %
b01 &
1'
1(
b01011 )
b1110101000011001 *
b1110000111100100 +
#38500
1$
#39000
0$
b110101100111001100001000001 !
b101011111110011001 "
b011111000000100010001000110010011101101010001010 #
b110001001001100001110010110 %
b11 &
1'
0(
b00010 )
b1011100110111000 *
b0000101001010111 +
#39500
1$
#40000
0$
b000101011010110110011010100 !
b001000100000110101 "
b001010101010001100101011011100010001001101000011 #
b111010010011011001111110110 %
b10 &
0'
0(
b11000 )
b0101010100001101 *
b1001100110100111 +
#40500
1$
#41000
0$
b100000011000000111101000010 !
b110101110101010001 "
b010111100011110001000001010110101100010000000000 #
b010101101011111011111010001 %
b01 &
0'
0(
b00111 )
b1101111000001111 *
b1111000110101001 +
#41500
1$
#42000
0$
b100110101001111010011001010 !
b110001111000111111 "
b101101110001000111110100010011010111111001000000 #
b111000110010001111001110010 %
b01 &
0'
1(
b10001 )
b1100010100101111 *
b0001101010110001 +
#42500
1$
#43000
0$
b010100100001101100011000101 !
b000010100000010011 "
b000100101011110001101000000101101101111000000110 #
b011000010101011011000100110 %
b11 &
1'
1(
b00100 )
b1101010000011000 *
b0010000000000001 +
#43500
1$
#44000
0$
b010101110100010100001110011 !
b000111010101110001 "
b100101100110000010011101011111001101010011110110 #
b110010000010101011010101100 %
b11 &
0'
0(
b10010 )
b1000110011011110 *
b0011100101000101 +
#44500
1$
#45000
0$
b100100001110001100101110100 !
b000101001110110100 "
b010001000100100011110011110001100110100010110001 #
b010111010110100110001100100 %
b11 &
0'
1(
b10001 )
b1110110011010001 *
b0001110101000011 +
#45500
1$
#46000
0$
b011101010011000001011101101 !
b111001011001001000 "
b000110111001010001000110111101010111001100100111 #
b110010010111100111001011000 %
b00 &
1'
0(
b00000 )
b1001110100011001 *
b1010101110100000 +
#46500
1$
#47000
0$
b000000111011100101101101100 !
b000101110111100010 "
b000111010111011101101001110111010110010010010011 #
b110100110111110010011001011 %
b11 &
1'
0(
b00110 )
b0011110101011000 *
b1100100100010111 +
#47500
1$
#48000
0$
b111111001111011111110100100 !
b100101100011100000 "
b001010010111101001101011110001111000101111110101 #
b000111011001010100111000100 %
b01 &
0'
1(
b00111 )
b0010100010110000 *
b1011111001110111 +
#48500
1$
#49000
0$
b110110000101001100101000101 !
b000110100101001101 "
b111010010010011101101111011000101110011000111010 #
b111101101111011000101100001 %
b01 &
1'
1(
b10001 )
b1110100011000010 *
b1101000101111111 +
#49500
1$
#50000
0$
b010010110100010100100001001 !
b100011001101101010 "
b101101100010110001000000110111110111110010011010 #
b011110100001110101010101011 %
b01 &
0'
0(
b10100 )
b0101000101000010 *
b0000101000100100 +
#50500
1$
#51000
0$
b000001101111101010101101101 !
b000000101011000010 "
b111110111000101011001001011011111010011101011000 #
b111011001111010001011100110 %
b01 &
1'
1(
b01010 )
b0111001100101001 *
b0110010000101010 +
#51500
1$
#52000
0$
b010100000011001100101100101 !
b011001100000011110 "
b000100000110111000010000000111100111010111101011 #
b111010011101010000001111001 %
b01 &
1'
1(
b11111 )
b0111010010110011 *
b0001110010000010 +
#52500
1$
#53000
0$
b010000000000010000011110000 !
b001101110001011011 "
b100111100010100011001000111111101010010111010111 #
b110001110010010110111101100 %
b11 &
1'
1(
b11011 )
b1011000000101101 *
b0111100000001011 +
#53500
1$
#54000
0$
b101010010110110111111011001 !
b010110110001011101 "
b001011101110011101000010010100110111010110111110 #
b100010101010011001110010001 %
b00 &
0'
0(
b00111 )
b0101110001000111 *
b0001010011010100 +
#54500
1$
#55000
0$
b110100011110101000000100000 !
b010001111110000110 "
b111110111011111000010110111000111110001110000000 #
b110000001101011101100101011 %
b01 &
0'
1(
b10010 )
b1010010010111010 *
b0101011011000001 +
#55500
1$
#56000
0$
b111100001101001111111010010 !
b001110100011100010 "
b111101110111001001100011111101100110011011100000 #
b010011101000100101101010011 %
b00 &
0'
0(
b01010 )
b1100101011110000 *
b1101100011011101 +
#56500
1$
#57000
0$
b100101000011100111000111010 !
b111001001011110001 "
b010011011000010011101011110111011011000010011000 #
b001111101110111111100111001 %
b01 &
0'
1(
b10011 )
b1001010000111000 *
b1100111010111100 +
#57500
1$
#58000
0$
b100110001001000100000000010 !
b000101111001000000 "
b001110000101110000111110101111101011111000111110 #
b000001010011011100111011011 %
b11 &
0'
0(
b00010 )
b0100010010011111 *
b1000110100011011 +
#58500
1$
#59000
0$
b110111100001100000100111010 !
b000100100010011110 "
b000100110011101110111010101010101101011001010001 #
b000001011000000111110010010 %
b10 &
0'
0(
b11000 )
b1100101011001100 *
b0101101111110011 +
#59500
1$
#60000
0$
b011111100100011001011011000 !
b011110000000010110 "
b110110111110111011011100110101101001000000101001 #
b001001110111100001010000011 %
b00 &
1'
1(
b11001 )
b0101001111111101 *
b0001001110111101 +
#60500
1$
#61000
0$
b100000100101111110000101010 !
b111100110000000010 "
b001011000101100110101010010011011010100000100010 #
b001011011111100000010000101 %
b11 &
0'
1(
b00100 )
b1101001001010001 *
b1101110110010100 +
#61500
1$
#62000
0$
b010100011101110101011101010 !
b010011100011110101 "
b101101011001011000011011010111000101011011010011 #
b100000111010110011111011011 %
b11 &
1'
1(
b01001 )
b0010000001010101 *
b1110010011001101 +
#62500
1$
#63000
0$
b001101001110110011110010111 !
b001001000100010100 "
b111010010001010110001011101001010110110100110100 #
b101110001111111000101111010 %
b00 &
1'
0(
b11010 )
b1110011100110000 *
b1001111110011111 +
#63500
1$
#64000
0$
b110011011100100110000110011 !
b101011000001010100 "
b100011011000111011101000001110110011101010110001 #
b110101110011100101010100001 %
b11 &
1'
1(
b10110 )
b0011010010010111 *
b0010110110011011 +
#64500
1$
#65000
0$
b010011001000011001110000011 !
b011011101100000101 "
b001010000110101110001001100110010001100010100111 #
b000011000110111001011001011 %
b10 &
1'
1(
b00111 )
b0100000010101001 *
b1100011100011100 +
#65500
1$
#66000
0$
b000100000111110101110010110 !
b101011101001110010 "
b011100100101101011110110101000000111010100000000 #
b110011101110100110100100111 %
b01 &
1'
0(
b10001 )
b0111000001111100 *
b1101100111101110 +
#66500
1$
#67000
0$
b100010011011111001001011010 !
b011101000000110000 "
b011001010100110100000010110010000010011000011011 #
b110101100001011100101010110 %
b01 &
0'
0(
b01111 )
b0000011000111111 *
b1100101100000110 +
#67500
1$
#68000
0$
b101001010111110100000100000 !
b111011101100000101 "
b111110011110111101101010101010111100101101111000 #
b100100100001001100010100011 %
b00 &
0'
1(
b01011 )
b1001010001111111 *
b0010001101100110 +
#68500
1$
#69000
0$
b100101111111001010100111000 !
b001000000000100001 "
b010000100101010100100011011101000111010111100001 #
b111110111011010000011101000 %
b11 &
0'
0(
b10010 )
b0110011010101101 *
b0010110000010011 +
#69500
1$
#70000
0$
b100111001100100100110000110 !
b000101101101100011 "
b011111000110101000111011110010001001100101101011 #
b000000011110101000000110001 %
b00 &
1'
0(
b10000 )
b1110010010011101 *
b1010011000011010 +
#70500
1$
#71000
0$
b111010111010000110101001110 !
b011100000011010110 "
b101011111011111111101110000110111000110011000100 #
b101000111001110011000100101 %
b10 &
0'
0(
b01010 )
b0111111010111101 *
b1010111111011011 +
#71500
1$
#72000
0$
b011110101001010001100110000 !
b111101001101111111 "
b101101100111110100111001100111011010101100111100 #
b011010011000100011110110011 %
b01 &
1'
1(
b11101 )
b1011101001101100 *
b1110101011101110 +
#72500
1$
#73000
0$
b101001110100010110111010011 !
b010001100111010100 "
b101001010111101111111000111011000010110100110100 #
b001110000010111100100001111 %
b00 &
1'
0(
b11000 )
b1000001011111110 *
b1010010100110001 +
#73500
1$
#74000
0$
b111000001001111011011101010 !
b010111100110001001 "
b100000101111101000101000110100101110000010001110 #
b110001000001101001100110110 %
b11 &
1'
0(
b01001 )
b0100110001111000 *
b1011000101001011 +
#74500
1$
#75000
0$
b010011001011000001011110110 !
b110110010101011101 "
b010111110010001010001101011001001011001110101101 #
b001010100100100100100110111 %
b10 &
1'
1(
b01110 )
b1001100000110110 *
b0001010111000000 +
#75500
1$
#76000
0$
b110110110011010011111010100 !
b000111111000110011 "
b100110110010100111100101100001111101110100100001 #
b111101011100011110111001101 %
b10 &
1'
0(
b00101 )
b0010011111100001 *
b0100000000100111 +
#76500
1$
#77000
0$
b011011010011111110101101010 !
b001101111011010111 "
b100100011100101111110001000100101100111111010000 #
b101110000011011110001101100 %
b11 &
1'
0(
b01111 )
b1010111001111111 *
b0110010011000011 +
#77500
1$
#78000
0$
b101101111001011101011011001 !
b101000110001000010 "
b011000100100110001011001000101010101000011111111 #
b100000111101101010110010011 %
b11 &
0'
1(
b10111 )
b1111111010001011 *
b0000101001101011 +
#78500
1$
